zdgram/__init__.py
zdgram/bot.py
zdgram/enums.py
zdgram/utils.py
zdgram/exceptions/__init__.py
zdgram/exceptions/api_exceptions.py
zdgram/handlers/__init__.py
zdgram/handlers/on_callback_query.py
zdgram/handlers/on_channel_post.py
zdgram/handlers/on_chat_join_request.py
zdgram/handlers/on_chat_member.py
zdgram/handlers/on_chosen_inline_result.py
zdgram/handlers/on_edited_channel_post.py
zdgram/handlers/on_edited_message.py
zdgram/handlers/on_inline_query.py
zdgram/handlers/on_message.py
zdgram/handlers/on_my_chat_member.py
zdgram/handlers/on_poll.py
zdgram/handlers/on_poll_answer.py
zdgram/handlers/on_pre_checkout_query.py
zdgram/handlers/on_shipping_query.py
zdgram/handlers/on_update.py
zdgram/methods/__init__.py
zdgram/methods/answer_callback_query.py
zdgram/methods/answer_inline_query.py
zdgram/methods/close.py
zdgram/methods/copy_message.py
zdgram/methods/delete_message.py
zdgram/methods/edit_message_caption.py
zdgram/methods/edit_message_media.py
zdgram/methods/edit_message_reply_markup.py
zdgram/methods/edit_message_text.py
zdgram/methods/forward_message.py
zdgram/methods/get_chat.py
zdgram/methods/get_me.py
zdgram/methods/listen.py
zdgram/methods/logout.py
zdgram/methods/send_animation.py
zdgram/methods/send_audio.py
zdgram/methods/send_document.py
zdgram/methods/send_location.py
zdgram/methods/send_media_group.py
zdgram/methods/send_message.py
zdgram/methods/send_photo.py
zdgram/methods/send_request.py
zdgram/methods/send_sticker.py
zdgram/methods/send_venue.py
zdgram/methods/send_video.py
zdgram/methods/send_video_note.py
zdgram/methods/send_voice.py
zdgram/methods/stop_poll.py
zdgram/types/__init__.py
zdgram/types/animation.py
zdgram/types/audio.py
zdgram/types/callback_game.py
zdgram/types/callbackquery.py
zdgram/types/chat.py
zdgram/types/chat_administrator_rights.py
zdgram/types/chat_invite_link.py
zdgram/types/chat_join_request.py
zdgram/types/chat_location.py
zdgram/types/chat_member.py
zdgram/types/chat_permissions.py
zdgram/types/chat_photo.py
zdgram-0.1.dev7.dist-info/LICENSE
zdgram-0.1.dev7.dist-info/METADATA
zdgram-0.1.dev7.dist-info/WHEEL
zdgram-0.1.dev7.dist-info/top_level.txt
zdgram-0.1.dev7.dist-info/RECORD
