Metadata-Version: 2.1
Name: zdgram
Version: 0.1.dev7
Summary: Python module based on https://core.telegram.org/bots/api
Author: ZAID
Author-email: y8838@hotmail.com
Keywords: bots,bot-api,telegram
Classifier: Development Status :: 1 - Planning
Classifier: Intended Audience :: Developers
Classifier: Programming Language :: Python :: 3
Classifier: Operating System :: Unix
Classifier: Operating System :: MacOS :: MacOS X
Classifier: Operating System :: Microsoft :: Windows
Requires-Python: ~=3.8
License-File: LICENSE
Requires-Dist: asyncio
Requires-Dist: aiohttp
